vw/__init__.py
vw/_utils.py
vw/config.py
vw/lazy.py
import_volkswagen-0.1.2.dist-info/LICENSE
import_volkswagen-0.1.2.dist-info/METADATA
import_volkswagen-0.1.2.dist-info/WHEEL
import_volkswagen-0.1.2.dist-info/RECORD
