Metadata-Version: 2.3
Name: import-volkswagen
Version: 0.1.2
Summary: Detect if running in a testing environment and control if methods act (either no-op in a test, or only act in a test)
License: MIT
Author: mshafer1
Author-email: 2565361+mshafer1@users.noreply.github.com
Requires-Python: >=3.8.1,<4.0.0
Classifier: Development Status :: 5 - Production/Stable
Classifier: Intended Audience :: Developers
Classifier: Intended Audience :: Manufacturing
Classifier: Intended Audience :: Science/Research
Classifier: License :: OSI Approved :: MIT License
Classifier: Operating System :: Microsoft :: Windows
Classifier: Operating System :: POSIX
Classifier: Programming Language :: Python :: 3
Classifier: Programming Language :: Python :: 3.9
Classifier: Programming Language :: Python :: 3.10
Classifier: Programming Language :: Python :: 3.11
Classifier: Programming Language :: Python :: 3.12
Classifier: Programming Language :: Python :: 3.13
Classifier: Programming Language :: Python :: 3.8
Classifier: Programming Language :: Python :: Implementation :: CPython
Classifier: Programming Language :: Python :: Implementation :: PyPy
Requires-Dist: python-decouple (>=3.8,<4.0)
Project-URL: Documentation, https://mshafer1.github.io/py-vw/
Project-URL: Repository, https://github.com/mshafer1/py-vw
